MANIFEST.in
README.md
README.rst
setup.py
AmeriResumeParser.egg-info/PKG-INFO
AmeriResumeParser.egg-info/SOURCES.txt
AmeriResumeParser.egg-info/dependency_links.txt
AmeriResumeParser.egg-info/entry_points.txt
AmeriResumeParser.egg-info/not-zip-safe
AmeriResumeParser.egg-info/requires.txt
AmeriResumeParser.egg-info/top_level.txt
pyresparser/CHANGELOG.md
pyresparser/__init__.py
pyresparser/command_line.py
pyresparser/constants.py
pyresparser/custom_t.py
pyresparser/meta.json
pyresparser/requirements.txt
pyresparser/resume_parser.py
pyresparser/skills.csv
pyresparser/tokenizer
pyresparser/utils.py
pyresparser/ner/cfg
pyresparser/ner/model
pyresparser/ner/moves
pyresparser/vocab/key2row
pyresparser/vocab/lexemes.bin
pyresparser/vocab/strings.json
pyresparser/vocab/vectors